trade_analyzer_client/__init__.py
trade_analyzer_client/client.py
trade_analyzer_client/models/__init__.py
trade_analyzer_client/models/commission_model.py
trade_analyzer_client/models/commission_rule.py
trade_analyzer_client/models/platform.py
trade_analyzer_client/models/strategy.py
trade_analyzer_client/models/strategy_type.py
rcpy_trade_analyzer_client-0.2.3.dist-info/WHEEL
rcpy_trade_analyzer_client-0.2.3.dist-info/METADATA
rcpy_trade_analyzer_client-0.2.3.dist-info/RECORD
