Metadata-Version: 2.1
Name: rcpy-trade-analyzer-client
Version: 0.2.3
License: None
Author-email: Mengsyue Amao Tsai <mengsyue.tsai@outlook.com>
Requires-Python: >=3.9
Requires-Dist: requests>=2.28.1
